{
 "elo": [
  {
   "team": "Argentina",
   "elo": 2131,
   "delta": 11
  },
  {
   "team": "Spain",
   "elo": 2078,
   "delta": -22
  },
  {
   "team": "France",
   "elo": 2067,
   "delta": 17
  },
  {
   "team": "England",
   "elo": 2040,
   "delta": 0
  },
  {
   "team": "Brazil",
   "elo": 2013,
   "delta": -7
  },
  {
   "team": "Portugal",
   "elo": 1992,
   "delta": -18
  },
  {
   "team": "Netherlands",
   "elo": 1982,
   "delta": -8
  },
  {
   "team": "Germany",
   "elo": 1975,
   "delta": 15
  },
  {
   "team": "Belgium",
   "elo": 1939,
   "delta": -11
  },
  {
   "team": "Croatia",
   "elo": 1930,
   "delta": 0
  },
  {
   "team": "Morocco",
   "elo": 1927,
   "delta": 7
  },
  {
   "team": "Colombia",
   "elo": 1900,
   "delta": 0
  },
  {
   "team": "Japan",
   "elo": 1888,
   "delta": 8
  },
  {
   "team": "Uruguay",
   "elo": 1887,
   "delta": -13
  },
  {
   "team": "Mexico",
   "elo": 1879,
   "delta": 19
  },
  {
   "team": "Norway",
   "elo": 1872,
   "delta": 22
  },
  {
   "team": "USA",
   "elo": 1870,
   "delta": 30
  },
  {
   "team": "Austria",
   "elo": 1851,
   "delta": 21
  },
  {
   "team": "Sweden",
   "elo": 1842,
   "delta": 42
  },
  {
   "team": "South Korea",
   "elo": 1841,
   "delta": 21
  },
  {
   "team": "Switzerland",
   "elo": 1839,
   "delta": -11
  },
  {
   "team": "Ecuador",
   "elo": 1829,
   "delta": -31
  },
  {
   "team": "Australia",
   "elo": 1825,
   "delta": 45
  },
  {
   "team": "Senegal",
   "elo": 1823,
   "delta": -17
  },
  {
   "team": "Ivory Coast",
   "elo": 1811,
   "delta": 31
  },
  {
   "team": "Iran",
   "elo": 1810,
   "delta": -10
  },
  {
   "team": "Turkey",
   "elo": 1805,
   "delta": -45
  },
  {
   "team": "Egypt",
   "elo": 1801,
   "delta": 11
  },
  {
   "team": "Canada",
   "elo": 1784,
   "delta": -6
  },
  {
   "team": "Scotland",
   "elo": 1774,
   "delta": 14
  },
  {
   "team": "Algeria",
   "elo": 1769,
   "delta": -11
  },
  {
   "team": "Bosnia & Herzegovina",
   "elo": 1766,
   "delta": 6
  },
  {
   "team": "Paraguay",
   "elo": 1750,
   "delta": -30
  },
  {
   "team": "Ghana",
   "elo": 1750,
   "delta": 0
  },
  {
   "team": "Czech Republic",
   "elo": 1749,
   "delta": -21
  },
  {
   "team": "Panama",
   "elo": 1730,
   "delta": 0
  },
  {
   "team": "Tunisia",
   "elo": 1718,
   "delta": -42
  },
  {
   "team": "DR Congo",
   "elo": 1718,
   "delta": 18
  },
  {
   "team": "Saudi Arabia",
   "elo": 1713,
   "delta": 13
  },
  {
   "team": "South Africa",
   "elo": 1701,
   "delta": -19
  },
  {
   "team": "Uzbekistan",
   "elo": 1700,
   "delta": 0
  },
  {
   "team": "Qatar",
   "elo": 1691,
   "delta": 11
  },
  {
   "team": "New Zealand",
   "elo": 1680,
   "delta": 10
  },
  {
   "team": "Cape Verde",
   "elo": 1672,
   "delta": 22
  },
  {
   "team": "Jordan",
   "elo": 1649,
   "delta": -21
  },
  {
   "team": "Iraq",
   "elo": 1638,
   "delta": -22
  },
  {
   "team": "Curaçao",
   "elo": 1625,
   "delta": -15
  },
  {
   "team": "Haiti",
   "elo": 1586,
   "delta": -14
  }
 ],
 "elo_history": {
  "Argentina": [
   2120,
   2131
  ],
  "Spain": [
   2100,
   2078
  ],
  "France": [
   2050,
   2067
  ],
  "England": [
   2040
  ],
  "Brazil": [
   2020,
   2013
  ],
  "Portugal": [
   2010,
   1992
  ],
  "Netherlands": [
   1990,
   1982
  ],
  "Germany": [
   1960,
   1975
  ],
  "Belgium": [
   1950,
   1939
  ],
  "Croatia": [
   1930
  ],
  "Morocco": [
   1920,
   1927
  ],
  "Uruguay": [
   1900,
   1887
  ],
  "Colombia": [
   1900
  ],
  "Japan": [
   1880,
   1888
  ],
  "Mexico": [
   1860,
   1879
  ],
  "Ecuador": [
   1860,
   1829
  ],
  "Switzerland": [
   1850,
   1839
  ],
  "Turkey": [
   1850,
   1805
  ],
  "Norway": [
   1850,
   1872
  ],
  "USA": [
   1840,
   1870
  ],
  "Senegal": [
   1840,
   1823
  ],
  "Austria": [
   1830,
   1851
  ],
  "Iran": [
   1820,
   1810
  ],
  "South Korea": [
   1820,
   1841
  ],
  "Sweden": [
   1800,
   1842
  ],
  "Canada": [
   1790,
   1784
  ],
  "Egypt": [
   1790,
   1801
  ],
  "Algeria": [
   1780,
   1769
  ],
  "Ivory Coast": [
   1780,
   1811
  ],
  "Paraguay": [
   1780,
   1750
  ],
  "Australia": [
   1780,
   1825
  ],
  "Czech Republic": [
   1770,
   1749
  ],
  "Scotland": [
   1760,
   1774
  ],
  "Tunisia": [
   1760,
   1718
  ],
  "Bosnia & Herzegovina": [
   1760,
   1766
  ],
  "Ghana": [
   1750
  ],
  "Panama": [
   1730
  ],
  "South Africa": [
   1720,
   1701
  ],
  "Saudi Arabia": [
   1700,
   1713
  ],
  "Uzbekistan": [
   1700
  ],
  "DR Congo": [
   1700,
   1718
  ],
  "Qatar": [
   1680,
   1691
  ],
  "New Zealand": [
   1670,
   1680
  ],
  "Jordan": [
   1670,
   1649
  ],
  "Iraq": [
   1660,
   1638
  ],
  "Cape Verde": [
   1650,
   1672
  ],
  "Curaçao": [
   1640,
   1625
  ],
  "Haiti": [
   1600,
   1586
  ]
 },
 "per_match": {
  "1": {
   "prediction": {
    "p1": 0.6418,
    "pd": 0.2035,
    "p2": 0.1544,
    "score": [
     2,
     0
    ],
    "lambdas": [
     2.05,
     0.89
    ]
   },
   "elo_before": [
    1860,
    1720
   ],
   "elo_delta": 18.8
  },
  "2": {
   "prediction": {
    "p1": 0.4409,
    "pd": 0.254,
    "p2": 0.3051,
    "score": [
     1,
     1
    ],
    "lambdas": [
     1.51,
     1.21
    ]
   },
   "elo_before": [
    1820,
    1770
   ],
   "elo_delta": 21.4
  },
  "7": {
   "prediction": {
    "p1": 0.4841,
    "pd": 0.2476,
    "p2": 0.2682,
    "score": [
     1,
     1
    ],
    "lambdas": [
     1.61,
     1.13
    ]
   },
   "elo_before": [
    1790,
    1760
   ],
   "elo_delta": -5.7
  },
  "19": {
   "prediction": {
    "p1": 0.5276,
    "pd": 0.2386,
    "p2": 0.2337,
    "score": [
     1,
     1
    ],
    "lambdas": [
     1.72,
     1.06
    ]
   },
   "elo_before": [
    1840,
    1780
   ],
   "elo_delta": 30.3
  },
  "8": {
   "prediction": {
    "p1": 0.1724,
    "pd": 0.2135,
    "p2": 0.6139,
    "score": [
     0,
     1
    ],
    "lambdas": [
     0.93,
     1.96
    ]
   },
   "elo_before": [
    1680,
    1850
   ],
   "elo_delta": 11.3
  },
  "13": {
   "prediction": {
    "p1": 0.5131,
    "pd": 0.2419,
    "p2": 0.2449,
    "score": [
     1,
     1
    ],
    "lambdas": [
     1.68,
     1.08
    ]
   },
   "elo_before": [
    2020,
    1920
   ],
   "elo_delta": -7.0
  },
  "14": {
   "prediction": {
    "p1": 0.1819,
    "pd": 0.2183,
    "p2": 0.5997,
    "score": [
     0,
     1
    ],
    "lambdas": [
     0.95,
     1.92
    ]
   },
   "elo_before": [
    1600,
    1760
   ],
   "elo_delta": -14.2
  },
  "20": {
   "prediction": {
    "p1": 0.2802,
    "pd": 0.2501,
    "p2": 0.4696,
    "score": [
     1,
     1
    ],
    "lambdas": [
     1.16,
     1.57
    ]
   },
   "elo_before": [
    1780,
    1850
   ],
   "elo_delta": 45.0
  },
  "25": {
   "prediction": {
    "p1": 0.8022,
    "pd": 0.1292,
    "p2": 0.0666,
    "score": [
     2,
     0
    ],
    "lambdas": [
     2.72,
     0.67
    ]
   },
   "elo_before": [
    1960,
    1640
   ],
   "elo_delta": 14.5
  },
  "26": {
   "prediction": {
    "p1": 0.2682,
    "pd": 0.2476,
    "p2": 0.4841,
    "score": [
     1,
     1
    ],
    "lambdas": [
     1.13,
     1.61
    ]
   },
   "elo_before": [
    1780,
    1860
   ],
   "elo_delta": 30.7
  },
  "31": {
   "prediction": {
    "p1": 0.5276,
    "pd": 0.2386,
    "p2": 0.2337,
    "score": [
     1,
     1
    ],
    "lambdas": [
     1.72,
     1.06
    ]
   },
   "elo_before": [
    1990,
    1880
   ],
   "elo_delta": -7.7
  },
  "32": {
   "prediction": {
    "p1": 0.4266,
    "pd": 0.2555,
    "p2": 0.3178,
    "score": [
     1,
     1
    ],
    "lambdas": [
     1.47,
     1.24
    ]
   },
   "elo_before": [
    1800,
    1760
   ],
   "elo_delta": 41.5
  },
  "37": {
   "prediction": {
    "p1": 0.5997,
    "pd": 0.2183,
    "p2": 0.1819,
    "score": [
     1,
     0
    ],
    "lambdas": [
     1.92,
     0.95
    ]
   },
   "elo_before": [
    1950,
    1790
   ],
   "elo_delta": -10.8
  },
  "38": {
   "prediction": {
    "p1": 0.5854,
    "pd": 0.2228,
    "p2": 0.1916,
    "score": [
     1,
     0
    ],
    "lambdas": [
     1.88,
     0.97
    ]
   },
   "elo_before": [
    1820,
    1670
   ],
   "elo_delta": -10.2
  },
  "43": {
   "prediction": {
    "p1": 0.9034,
    "pd": 0.0621,
    "p2": 0.0224,
    "score": [
     3,
     0
    ],
    "lambdas": [
     3.62,
     0.5
    ]
   },
   "elo_before": [
    2100,
    1650
   ],
   "elo_delta": -21.5
  },
  "44": {
   "prediction": {
    "p1": 0.1458,
    "pd": 0.1983,
    "p2": 0.6556,
    "score": [
     0,
     2
    ],
    "lambdas": [
     0.87,
     2.09
    ]
   },
   "elo_before": [
    1700,
    1900
   ],
   "elo_delta": 13.0
  },
  "49": {
   "prediction": {
    "p1": 0.6691,
    "pd": 0.1929,
    "p2": 0.1376,
    "score": [
     2,
     0
    ],
    "lambdas": [
     2.14,
     0.85
    ]
   },
   "elo_before": [
    2050,
    1840
   ],
   "elo_delta": 17.2
  },
  "50": {
   "prediction": {
    "p1": 0.1544,
    "pd": 0.2035,
    "p2": 0.6418,
    "score": [
     0,
     2
    ],
    "lambdas": [
     0.89,
     2.05
    ]
   },
   "elo_before": [
    1660,
    1850
   ],
   "elo_delta": -22.0
  },
  "55": {
   "prediction": {
    "p1": 0.8223,
    "pd": 0.1177,
    "p2": 0.0573,
    "score": [
     2,
     0
    ],
    "lambdas": [
     2.85,
     0.64
    ]
   },
   "elo_before": [
    2120,
    1780
   ],
   "elo_delta": 10.8
  },
  "56": {
   "prediction": {
    "p1": 0.5997,
    "pd": 0.2183,
    "p2": 0.1819,
    "score": [
     1,
     0
    ],
    "lambdas": [
     1.92,
     0.95
    ]
   },
   "elo_before": [
    1830,
    1670
   ],
   "elo_delta": 21.4
  },
  "61": {
   "prediction": {
    "p1": 0.7916,
    "pd": 0.135,
    "p2": 0.0716,
    "score": [
     2,
     0
    ],
    "lambdas": [
     2.66,
     0.68
    ]
   },
   "elo_before": [
    2010,
    1700
   ],
   "elo_delta": -17.8
  },
  "3": {
   "prediction": {
    "p1": 0.4372,
    "pd": 0.2544,
    "p2": 0.3084,
    "score": [
     1,
     1
    ],
    "lambdas": [
     1.5,
     1.22
    ]
   },
   "elo_before": [
    1749,
    1701
   ],
   "elo_delta": null
  },
  "4": {
   "prediction": {
    "p1": 0.4948,
    "pd": 0.2457,
    "p2": 0.2595,
    "score": [
     1,
     1
    ],
    "lambdas": [
     1.64,
     1.11
    ]
   },
   "elo_before": [
    1929,
    1841
   ],
   "elo_delta": null
  },
  "5": {
   "prediction": {
    "p1": 0.163,
    "pd": 0.2085,
    "p2": 0.6283,
    "score": [
     0,
     2
    ],
    "lambdas": [
     0.91,
     2.0
    ]
   },
   "elo_before": [
    1749,
    1929
   ],
   "elo_delta": null
  },
  "6": {
   "prediction": {
    "p1": 0.2014,
    "pd": 0.227,
    "p2": 0.5714,
    "score": [
     0,
     1
    ],
    "lambdas": [
     0.99,
     1.84
    ]
   },
   "elo_before": [
    1701,
    1841
   ],
   "elo_delta": null
  },
  "9": {
   "prediction": {
    "p1": 0.474,
    "pd": 0.2494,
    "p2": 0.2766,
    "score": [
     1,
     1
    ],
    "lambdas": [
     1.58,
     1.15
    ]
   },
   "elo_before": [
    1839,
    1766
   ],
   "elo_delta": null
  },
  "10": {
   "prediction": {
    "p1": 0.5754,
    "pd": 0.2258,
    "p2": 0.1986,
    "score": [
     1,
     0
    ],
    "lambdas": [
     1.85,
     0.99
    ]
   },
   "elo_before": [
    1834,
    1691
   ],
   "elo_delta": null
  },
  "11": {
   "prediction": {
    "p1": 0.3768,
    "pd": 0.2581,
    "p2": 0.365,
    "score": [
     1,
     1
    ],
    "lambdas": [
     1.36,
     1.34
    ]
   },
   "elo_before": [
    1839,
    1834
   ],
   "elo_delta": null
  },
  "12": {
   "prediction": {
    "p1": 0.4759,
    "pd": 0.2491,
    "p2": 0.275,
    "score": [
     1,
     1
    ],
    "lambdas": [
     1.59,
     1.15
    ]
   },
   "elo_before": [
    1766,
    1691
   ],
   "elo_delta": null
  },
  "15": {
   "prediction": {
    "p1": 0.1889,
    "pd": 0.2216,
    "p2": 0.5894,
    "score": [
     0,
     1
    ],
    "lambdas": [
     0.97,
     1.89
    ]
   },
   "elo_before": [
    1774,
    1927
   ],
   "elo_delta": null
  },
  "16": {
   "prediction": {
    "p1": 0.8912,
    "pd": 0.0722,
    "p2": 0.0277,
    "score": [
     3,
     0
    ],
    "lambdas": [
     3.45,
     0.53
    ]
   },
   "elo_before": [
    2013,
    1586
   ],
   "elo_delta": null
  },
  "17": {
   "prediction": {
    "p1": 0.1156,
    "pd": 0.1768,
    "p2": 0.707,
    "score": [
     0,
     2
    ],
    "lambdas": [
     0.8,
     2.28
    ]
   },
   "elo_before": [
    1774,
    2013
   ],
   "elo_delta": null
  },
  "18": {
   "prediction": {
    "p1": 0.8235,
    "pd": 0.1169,
    "p2": 0.0568,
    "score": [
     2,
     0
    ],
    "lambdas": [
     2.85,
     0.64
    ]
   },
   "elo_before": [
    1927,
    1586
   ],
   "elo_delta": null
  },
  "21": {
   "prediction": {
    "p1": 0.5064,
    "pd": 0.2433,
    "p2": 0.2502,
    "score": [
     1,
     1
    ],
    "lambdas": [
     1.66,
     1.1
    ]
   },
   "elo_before": [
    1920,
    1825
   ],
   "elo_delta": null
  },
  "22": {
   "prediction": {
    "p1": 0.4486,
    "pd": 0.2531,
    "p2": 0.2983,
    "score": [
     1,
     1
    ],
    "lambdas": [
     1.52,
     1.2
    ]
   },
   "elo_before": [
    1805,
    1750
   ],
   "elo_delta": null
  },
  "23": {
   "prediction": {
    "p1": 0.2279,
    "pd": 0.2367,
    "p2": 0.5353,
    "score": [
     1,
     1
    ],
    "lambdas": [
     1.05,
     1.74
    ]
   },
   "elo_before": [
    1805,
    1920
   ],
   "elo_delta": null
  },
  "24": {
   "prediction": {
    "p1": 0.2738,
    "pd": 0.2488,
    "p2": 0.4773,
    "score": [
     1,
     1
    ],
    "lambdas": [
     1.14,
     1.59
    ]
   },
   "elo_before": [
    1750,
    1825
   ],
   "elo_delta": null
  },
  "27": {
   "prediction": {
    "p1": 0.6052,
    "pd": 0.2165,
    "p2": 0.1781,
    "score": [
     1,
     0
    ],
    "lambdas": [
     1.93,
     0.94
    ]
   },
   "elo_before": [
    1975,
    1811
   ],
   "elo_delta": null
  },
  "28": {
   "prediction": {
    "p1": 0.6608,
    "pd": 0.1962,
    "p2": 0.1426,
    "score": [
     2,
     0
    ],
    "lambdas": [
     2.11,
     0.86
    ]
   },
   "elo_before": [
    1829,
    1625
   ],
   "elo_delta": null
  },
  "29": {
   "prediction": {
    "p1": 0.1586,
    "pd": 0.206,
    "p2": 0.6352,
    "score": [
     0,
     2
    ],
    "lambdas": [
     0.9,
     2.03
    ]
   },
   "elo_before": [
    1625,
    1811
   ],
   "elo_delta": null
  },
  "30": {
   "prediction": {
    "p1": 0.1964,
    "pd": 0.2249,
    "p2": 0.5785,
    "score": [
     0,
     1
    ],
    "lambdas": [
     0.98,
     1.86
    ]
   },
   "elo_before": [
    1829,
    1975
   ],
   "elo_delta": null
  },
  "33": {
   "prediction": {
    "p1": 0.5723,
    "pd": 0.2268,
    "p2": 0.2008,
    "score": [
     1,
     0
    ],
    "lambdas": [
     1.84,
     0.99
    ]
   },
   "elo_before": [
    1982,
    1842
   ],
   "elo_delta": null
  },
  "34": {
   "prediction": {
    "p1": 0.1732,
    "pd": 0.2139,
    "p2": 0.6127,
    "score": [
     0,
     1
    ],
    "lambdas": [
     0.93,
     1.96
    ]
   },
   "elo_before": [
    1718,
    1888
   ],
   "elo_delta": null
  },
  "35": {
   "prediction": {
    "p1": 0.4354,
    "pd": 0.2546,
    "p2": 0.3099,
    "score": [
     1,
     1
    ],
    "lambdas": [
     1.49,
     1.22
    ]
   },
   "elo_before": [
    1888,
    1842
   ],
   "elo_delta": null
  },
  "36": {
   "prediction": {
    "p1": 0.0984,
    "pd": 0.1622,
    "p2": 0.7385,
    "score": [
     0,
     2
    ],
    "lambdas": [
     0.76,
     2.41
    ]
   },
   "elo_before": [
    1718,
    1982
   ],
   "elo_delta": null
  },
  "39": {
   "prediction": {
    "p1": 0.5558,
    "pd": 0.2314,
    "p2": 0.2127,
    "score": [
     1,
     1
    ],
    "lambdas": [
     1.79,
     1.02
    ]
   },
   "elo_before": [
    1939,
    1810
   ],
   "elo_delta": null
  },
  "40": {
   "prediction": {
    "p1": 0.2221,
    "pd": 0.2348,
    "p2": 0.543,
    "score": [
     1,
     1
    ],
    "lambdas": [
     1.04,
     1.76
    ]
   },
   "elo_before": [
    1680,
    1801
   ],
   "elo_delta": null
  },
  "41": {
   "prediction": {
    "p1": 0.3586,
    "pd": 0.258,
    "p2": 0.3833,
    "score": [
     1,
     1
    ],
    "lambdas": [
     1.32,
     1.38
    ]
   },
   "elo_before": [
    1801,
    1810
   ],
   "elo_delta": null
  },
  "42": {
   "prediction": {
    "p1": 0.1015,
    "pd": 0.165,
    "p2": 0.7326,
    "score": [
     0,
     2
    ],
    "lambdas": [
     0.76,
     2.38
    ]
   },
   "elo_before": [
    1680,
    1939
   ],
   "elo_delta": null
  },
  "45": {
   "prediction": {
    "p1": 0.8458,
    "pd": 0.1034,
    "p2": 0.0469,
    "score": [
     3,
     0
    ],
    "lambdas": [
     3.01,
     0.61
    ]
   },
   "elo_before": [
    2078,
    1713
   ],
   "elo_delta": null
  },
  "46": {
   "prediction": {
    "p1": 0.6765,
    "pd": 0.1899,
    "p2": 0.1332,
    "score": [
     2,
     0
    ],
    "lambdas": [
     2.17,
     0.84
    ]
   },
   "elo_before": [
    1887,
    1672
   ],
   "elo_delta": null
  },
  "47": {
   "prediction": {
    "p1": 0.3159,
    "pd": 0.2553,
    "p2": 0.4287,
    "score": [
     1,
     1
    ],
    "lambdas": [
     1.23,
     1.48
    ]
   },
   "elo_before": [
    1672,
    1713
   ],
   "elo_delta": null
  },
  "48": {
   "prediction": {
    "p1": 0.1531,
    "pd": 0.2028,
    "p2": 0.6439,
    "score": [
     0,
     2
    ],
    "lambdas": [
     0.89,
     2.05
    ]
   },
   "elo_before": [
    1887,
    2078
   ],
   "elo_delta": null
  },
  "51": {
   "prediction": {
    "p1": 0.8923,
    "pd": 0.0713,
    "p2": 0.0272,
    "score": [
     3,
     0
    ],
    "lambdas": [
     3.46,
     0.53
    ]
   },
   "elo_before": [
    2067,
    1638
   ],
   "elo_delta": null
  },
  "52": {
   "prediction": {
    "p1": 0.4397,
    "pd": 0.2542,
    "p2": 0.3061,
    "score": [
     1,
     1
    ],
    "lambdas": [
     1.5,
     1.21
    ]
   },
   "elo_before": [
    1872,
    1823
   ],
   "elo_delta": null
  },
  "53": {
   "prediction": {
    "p1": 0.1498,
    "pd": 0.2008,
    "p2": 0.6491,
    "score": [
     0,
     2
    ],
    "lambdas": [
     0.88,
     2.07
    ]
   },
   "elo_before": [
    1872,
    2067
   ],
   "elo_delta": null
  },
  "54": {
   "prediction": {
    "p1": 0.6345,
    "pd": 0.2063,
    "p2": 0.159,
    "score": [
     2,
     0
    ],
    "lambdas": [
     2.02,
     0.9
    ]
   },
   "elo_before": [
    1823,
    1638
   ],
   "elo_delta": null
  },
  "57": {
   "prediction": {
    "p1": 0.7572,
    "pd": 0.153,
    "p2": 0.0887,
    "score": [
     2,
     0
    ],
    "lambdas": [
     2.49,
     0.73
    ]
   },
   "elo_before": [
    2131,
    1851
   ],
   "elo_delta": null
  },
  "58": {
   "prediction": {
    "p1": 0.2222,
    "pd": 0.2348,
    "p2": 0.5429,
    "score": [
     1,
     1
    ],
    "lambdas": [
     1.04,
     1.76
    ]
   },
   "elo_before": [
    1649,
    1769
   ],
   "elo_delta": null
  },
  "59": {
   "prediction": {
    "p1": 0.2656,
    "pd": 0.2471,
    "p2": 0.4873,
    "score": [
     1,
     1
    ],
    "lambdas": [
     1.13,
     1.62
    ]
   },
   "elo_before": [
    1769,
    1851
   ],
   "elo_delta": null
  },
  "60": {
   "prediction": {
    "p1": 0.0163,
    "pd": 0.0493,
    "p2": 0.9162,
    "score": [
     0,
     3
    ],
    "lambdas": [
     0.47,
     3.89
    ]
   },
   "elo_before": [
    1649,
    2131
   ],
   "elo_delta": null
  },
  "62": {
   "prediction": {
    "p1": 0.1458,
    "pd": 0.1983,
    "p2": 0.6556,
    "score": [
     0,
     2
    ],
    "lambdas": [
     0.87,
     2.09
    ]
   },
   "elo_before": [
    1700,
    1900
   ],
   "elo_delta": null
  },
  "63": {
   "prediction": {
    "p1": 0.7719,
    "pd": 0.1455,
    "p2": 0.0813,
    "score": [
     2,
     0
    ],
    "lambdas": [
     2.56,
     0.71
    ]
   },
   "elo_before": [
    1992,
    1700
   ],
   "elo_delta": null
  },
  "64": {
   "prediction": {
    "p1": 0.631,
    "pd": 0.2075,
    "p2": 0.1613,
    "score": [
     2,
     0
    ],
    "lambdas": [
     2.01,
     0.91
    ]
   },
   "elo_before": [
    1900,
    1718
   ],
   "elo_delta": null
  },
  "65": {
   "prediction": {
    "p1": 0.2539,
    "pd": 0.2443,
    "p2": 0.5018,
    "score": [
     1,
     1
    ],
    "lambdas": [
     1.1,
     1.65
    ]
   },
   "elo_before": [
    1900,
    1992
   ],
   "elo_delta": null
  },
  "66": {
   "prediction": {
    "p1": 0.3954,
    "pd": 0.2576,
    "p2": 0.3469,
    "score": [
     1,
     1
    ],
    "lambdas": [
     1.4,
     1.3
    ]
   },
   "elo_before": [
    1718,
    1700
   ],
   "elo_delta": null
  },
  "67": {
   "prediction": {
    "p1": 0.5276,
    "pd": 0.2386,
    "p2": 0.2337,
    "score": [
     1,
     1
    ],
    "lambdas": [
     1.72,
     1.06
    ]
   },
   "elo_before": [
    2040,
    1930
   ],
   "elo_delta": null
  },
  "68": {
   "prediction": {
    "p1": 0.3985,
    "pd": 0.2575,
    "p2": 0.344,
    "score": [
     1,
     1
    ],
    "lambdas": [
     1.41,
     1.29
    ]
   },
   "elo_before": [
    1750,
    1730
   ],
   "elo_delta": null
  },
  "69": {
   "prediction": {
    "p1": 0.7694,
    "pd": 0.1468,
    "p2": 0.0825,
    "score": [
     2,
     0
    ],
    "lambdas": [
     2.55,
     0.71
    ]
   },
   "elo_before": [
    2040,
    1750
   ],
   "elo_delta": null
  },
  "70": {
   "prediction": {
    "p1": 0.1458,
    "pd": 0.1983,
    "p2": 0.6556,
    "score": [
     0,
     2
    ],
    "lambdas": [
     0.87,
     2.09
    ]
   },
   "elo_before": [
    1730,
    1930
   ],
   "elo_delta": null
  },
  "71": {
   "prediction": {
    "p1": 0.0716,
    "pd": 0.135,
    "p2": 0.7916,
    "score": [
     0,
     2
    ],
    "lambdas": [
     0.68,
     2.66
    ]
   },
   "elo_before": [
    1730,
    2040
   ],
   "elo_delta": null
  },
  "72": {
   "prediction": {
    "p1": 0.6279,
    "pd": 0.2086,
    "p2": 0.1632,
    "score": [
     2,
     0
    ],
    "lambdas": [
     2.0,
     0.91
    ]
   },
   "elo_before": [
    1930,
    1750
   ],
   "elo_delta": null
  }
 },
 "sims": [
  {
   "team": "Argentina",
   "r32": 0.9996,
   "r16": 0.8011,
   "qf": 0.5559,
   "sf": 0.3941,
   "f": 0.3063,
   "champ": 0.2178
  },
  {
   "team": "Spain",
   "r32": 0.966,
   "r16": 0.8084,
   "qf": 0.6313,
   "sf": 0.4602,
   "f": 0.3207,
   "champ": 0.1857
  },
  {
   "team": "Brazil",
   "r32": 0.9833,
   "r16": 0.7627,
   "qf": 0.5642,
   "sf": 0.3946,
   "f": 0.1994,
   "champ": 0.1003
  },
  {
   "team": "France",
   "r32": 0.9993,
   "r16": 0.7209,
   "qf": 0.3618,
   "sf": 0.2239,
   "f": 0.156,
   "champ": 0.0968
  },
  {
   "team": "England",
   "r32": 0.9701,
   "r16": 0.6848,
   "qf": 0.4683,
   "sf": 0.2086,
   "f": 0.1383,
   "champ": 0.0786
  },
  {
   "team": "Netherlands",
   "r32": 0.9257,
   "r16": 0.6688,
   "qf": 0.4161,
   "sf": 0.2383,
   "f": 0.1214,
   "champ": 0.0579
  },
  {
   "team": "Germany",
   "r32": 0.997,
   "r16": 0.7123,
   "qf": 0.4466,
   "sf": 0.231,
   "f": 0.129,
   "champ": 0.0544
  },
  {
   "team": "Portugal",
   "r32": 0.9224,
   "r16": 0.5324,
   "qf": 0.3035,
   "sf": 0.1223,
   "f": 0.0757,
   "champ": 0.0374
  },
  {
   "team": "Morocco",
   "r32": 0.9518,
   "r16": 0.6386,
   "qf": 0.3985,
   "sf": 0.2226,
   "f": 0.08,
   "champ": 0.0304
  },
  {
   "team": "Belgium",
   "r32": 0.9126,
   "r16": 0.5721,
   "qf": 0.2758,
   "sf": 0.1509,
   "f": 0.069,
   "champ": 0.0276
  },
  {
   "team": "Croatia",
   "r32": 0.8761,
   "r16": 0.473,
   "qf": 0.1956,
   "sf": 0.0669,
   "f": 0.0334,
   "champ": 0.0128
  },
  {
   "team": "Japan",
   "r32": 0.8423,
   "r16": 0.4833,
   "qf": 0.2387,
   "sf": 0.1079,
   "f": 0.0375,
   "champ": 0.0123
  },
  {
   "team": "Mexico",
   "r32": 0.9845,
   "r16": 0.5759,
   "qf": 0.3165,
   "sf": 0.1403,
   "f": 0.0452,
   "champ": 0.0121
  },
  {
   "team": "USA",
   "r32": 0.9918,
   "r16": 0.5694,
   "qf": 0.241,
   "sf": 0.1238,
   "f": 0.0376,
   "champ": 0.0108
  },
  {
   "team": "Uruguay",
   "r32": 0.7611,
   "r16": 0.4323,
   "qf": 0.2189,
   "sf": 0.1088,
   "f": 0.0368,
   "champ": 0.0095
  },
  {
   "team": "Colombia",
   "r32": 0.8762,
   "r16": 0.3977,
   "qf": 0.1594,
   "sf": 0.0499,
   "f": 0.0237,
   "champ": 0.0081
  },
  {
   "team": "South Korea",
   "r32": 0.9478,
   "r16": 0.4884,
   "qf": 0.2344,
   "sf": 0.0928,
   "f": 0.0243,
   "champ": 0.0074
  },
  {
   "team": "Sweden",
   "r32": 0.966,
   "r16": 0.4805,
   "qf": 0.204,
   "sf": 0.0782,
   "f": 0.0234,
   "champ": 0.006
  },
  {
   "team": "Norway",
   "r32": 0.9712,
   "r16": 0.3072,
   "qf": 0.0937,
   "sf": 0.035,
   "f": 0.0139,
   "champ": 0.0047
  },
  {
   "team": "Australia",
   "r32": 0.9512,
   "r16": 0.4781,
   "qf": 0.1827,
   "sf": 0.0721,
   "f": 0.0166,
   "champ": 0.0046
  },
  {
   "team": "Switzerland",
   "r32": 0.7311,
   "r16": 0.3356,
   "qf": 0.1633,
   "sf": 0.0615,
   "f": 0.0168,
   "champ": 0.0035
  },
  {
   "team": "Ivory Coast",
   "r32": 0.9562,
   "r16": 0.4272,
   "qf": 0.1661,
   "sf": 0.0619,
   "f": 0.0143,
   "champ": 0.0034
  },
  {
   "team": "Ecuador",
   "r32": 0.64,
   "r16": 0.2799,
   "qf": 0.1148,
   "sf": 0.0441,
   "f": 0.011,
   "champ": 0.0028
  },
  {
   "team": "Austria",
   "r32": 0.9352,
   "r16": 0.2751,
   "qf": 0.0651,
   "sf": 0.0217,
   "f": 0.0074,
   "champ": 0.0021
  },
  {
   "team": "Canada",
   "r32": 0.7829,
   "r16": 0.3016,
   "qf": 0.1264,
   "sf": 0.0411,
   "f": 0.0099,
   "champ": 0.0021
  },
  {
   "team": "Iran",
   "r32": 0.5793,
   "r16": 0.2329,
   "qf": 0.0814,
   "sf": 0.0291,
   "f": 0.007,
   "champ": 0.0018
  },
  {
   "team": "Turkey",
   "r32": 0.4322,
   "r16": 0.1752,
   "qf": 0.0682,
   "sf": 0.0227,
   "f": 0.005,
   "champ": 0.0017
  },
  {
   "team": "Egypt",
   "r32": 0.7573,
   "r16": 0.2965,
   "qf": 0.1029,
   "sf": 0.0353,
   "f": 0.0086,
   "champ": 0.0015
  },
  {
   "team": "Senegal",
   "r32": 0.6405,
   "r16": 0.1911,
   "qf": 0.0704,
   "sf": 0.0233,
   "f": 0.0065,
   "champ": 0.0014
  },
  {
   "team": "Scotland",
   "r32": 0.7746,
   "r16": 0.2956,
   "qf": 0.1107,
   "sf": 0.0345,
   "f": 0.0058,
   "champ": 0.0011
  },
  {
   "team": "Bosnia & Herzegovina",
   "r32": 0.6828,
   "r16": 0.2378,
   "qf": 0.0898,
   "sf": 0.0254,
   "f": 0.0043,
   "champ": 0.001
  },
  {
   "team": "Algeria",
   "r32": 0.4915,
   "r16": 0.125,
   "qf": 0.0346,
   "sf": 0.0102,
   "f": 0.0021,
   "champ": 0.0005
  },
  {
   "team": "Czech Republic",
   "r32": 0.435,
   "r16": 0.1402,
   "qf": 0.0391,
   "sf": 0.0116,
   "f": 0.0032,
   "champ": 0.0005
  },
  {
   "team": "Paraguay",
   "r32": 0.3081,
   "r16": 0.0976,
   "qf": 0.0303,
   "sf": 0.0088,
   "f": 0.0017,
   "champ": 0.0003
  },
  {
   "team": "Saudi Arabia",
   "r32": 0.4821,
   "r16": 0.1394,
   "qf": 0.0369,
   "sf": 0.0079,
   "f": 0.0018,
   "champ": 0.0003
  },
  {
   "team": "Ghana",
   "r32": 0.4112,
   "r16": 0.1201,
   "qf": 0.0285,
   "sf": 0.0073,
   "f": 0.0016,
   "champ": 0.0002
  },
  {
   "team": "Tunisia",
   "r32": 0.0955,
   "r16": 0.0278,
   "qf": 0.0072,
   "sf": 0.0006,
   "f": 0.0001,
   "champ": 0.0001
  },
  {
   "team": "Panama",
   "r32": 0.3483,
   "r16": 0.0898,
   "qf": 0.0198,
   "sf": 0.0046,
   "f": 0.0009,
   "champ": 0.0001
  },
  {
   "team": "Uzbekistan",
   "r32": 0.3513,
   "r16": 0.0714,
   "qf": 0.0154,
   "sf": 0.0025,
   "f": 0.0007,
   "champ": 0.0001
  },
  {
   "team": "DR Congo",
   "r32": 0.5425,
   "r16": 0.1175,
   "qf": 0.0272,
   "sf": 0.0055,
   "f": 0.0013,
   "champ": 0.0001
  },
  {
   "team": "Qatar",
   "r32": 0.458,
   "r16": 0.1124,
   "qf": 0.0295,
   "sf": 0.0061,
   "f": 0.0007,
   "champ": 0.0001
  },
  {
   "team": "Cape Verde",
   "r32": 0.4532,
   "r16": 0.1162,
   "qf": 0.0231,
   "sf": 0.0045,
   "f": 0.0002,
   "champ": 0.0001
  },
  {
   "team": "South Africa",
   "r32": 0.2977,
   "r16": 0.0806,
   "qf": 0.0197,
   "sf": 0.0038,
   "f": 0.0005,
   "champ": 0.0
  },
  {
   "team": "New Zealand",
   "r32": 0.3377,
   "r16": 0.0778,
   "qf": 0.0149,
   "sf": 0.0029,
   "f": 0.0003,
   "champ": 0.0
  },
  {
   "team": "Jordan",
   "r32": 0.0924,
   "r16": 0.0157,
   "qf": 0.0028,
   "sf": 0.0006,
   "f": 0.0001,
   "champ": 0.0
  },
  {
   "team": "Iraq",
   "r32": 0.0569,
   "r16": 0.009,
   "qf": 0.0016,
   "sf": 0.0,
   "f": 0.0,
   "champ": 0.0
  },
  {
   "team": "Curaçao",
   "r32": 0.0982,
   "r16": 0.0179,
   "qf": 0.0029,
   "sf": 0.0003,
   "f": 0.0,
   "champ": 0.0
  },
  {
   "team": "Haiti",
   "r32": 0.0323,
   "r16": 0.0052,
   "qf": 0.0005,
   "sf": 0.0,
   "f": 0.0,
   "champ": 0.0
  }
 ],
 "n_sims": 10000,
 "upsets": [
  {
   "num": 26,
   "slug": "2026-06-14-ivory-coast-vs-ecuador",
   "date": "2026-06-14",
   "winner": "Ivory Coast",
   "loser": "Ecuador",
   "score": "1–0",
   "win_prob": 0.268
  },
  {
   "num": 20,
   "slug": "2026-06-13-australia-vs-turkey",
   "date": "2026-06-13",
   "winner": "Australia",
   "loser": "Turkey",
   "score": "2–0",
   "win_prob": 0.28
  },
  {
   "num": 32,
   "slug": "2026-06-14-sweden-vs-tunisia",
   "date": "2026-06-14",
   "winner": "Sweden",
   "loser": "Tunisia",
   "score": "5–1",
   "win_prob": 0.427
  },
  {
   "num": 2,
   "slug": "2026-06-11-south-korea-vs-czech-republic",
   "date": "2026-06-11",
   "winner": "South Korea",
   "loser": "Czech Republic",
   "score": "2–1",
   "win_prob": 0.441
  }
 ],
 "brier": 0.6639,
 "n_scored": 21,
 "goal_timing": [
  6,
  11,
  11,
  8,
  9,
  19
 ],
 "top_scorers": [
  {
   "name": "Lionel Messi",
   "goals": 3,
   "team": "Argentina"
  },
  {
   "name": "Elijah Just",
   "goals": 2,
   "team": "New Zealand"
  },
  {
   "name": "Erling Haaland",
   "goals": 2,
   "team": "Norway"
  },
  {
   "name": "Folarin Balogun",
   "goals": 2,
   "team": "USA"
  },
  {
   "name": "Kai Havertz",
   "goals": 2,
   "team": "Germany"
  },
  {
   "name": "Kylian Mbappé",
   "goals": 2,
   "team": "France"
  },
  {
   "name": "Yasin Ayari",
   "goals": 2,
   "team": "Sweden"
  },
  {
   "name": "Abdulelah Al-Amri",
   "goals": 1,
   "team": "Saudi Arabia"
  },
  {
   "name": "Alexander Isak",
   "goals": 1,
   "team": "Sweden"
  },
  {
   "name": "Ali Olwan",
   "goals": 1,
   "team": "Jordan"
  }
 ],
 "standings": {
  "Group A": [
   {
    "team": "Mexico",
    "p": 1,
    "w": 1,
    "d": 0,
    "l": 0,
    "gf": 2,
    "ga": 0,
    "pts": 3,
    "gd": 2
   },
   {
    "team": "South Korea",
    "p": 1,
    "w": 1,
    "d": 0,
    "l": 0,
    "gf": 2,
    "ga": 1,
    "pts": 3,
    "gd": 1
   },
   {
    "team": "Czech Republic",
    "p": 1,
    "w": 0,
    "d": 0,
    "l": 1,
    "gf": 1,
    "ga": 2,
    "pts": 0,
    "gd": -1
   },
   {
    "team": "South Africa",
    "p": 1,
    "w": 0,
    "d": 0,
    "l": 1,
    "gf": 0,
    "ga": 2,
    "pts": 0,
    "gd": -2
   }
  ],
  "Group B": [
   {
    "team": "Bosnia & Herzegovina",
    "p": 1,
    "w": 0,
    "d": 1,
    "l": 0,
    "gf": 1,
    "ga": 1,
    "pts": 1,
    "gd": 0
   },
   {
    "team": "Canada",
    "p": 1,
    "w": 0,
    "d": 1,
    "l": 0,
    "gf": 1,
    "ga": 1,
    "pts": 1,
    "gd": 0
   },
   {
    "team": "Qatar",
    "p": 1,
    "w": 0,
    "d": 1,
    "l": 0,
    "gf": 1,
    "ga": 1,
    "pts": 1,
    "gd": 0
   },
   {
    "team": "Switzerland",
    "p": 1,
    "w": 0,
    "d": 1,
    "l": 0,
    "gf": 1,
    "ga": 1,
    "pts": 1,
    "gd": 0
   }
  ],
  "Group C": [
   {
    "team": "Scotland",
    "p": 1,
    "w": 1,
    "d": 0,
    "l": 0,
    "gf": 1,
    "ga": 0,
    "pts": 3,
    "gd": 1
   },
   {
    "team": "Brazil",
    "p": 1,
    "w": 0,
    "d": 1,
    "l": 0,
    "gf": 1,
    "ga": 1,
    "pts": 1,
    "gd": 0
   },
   {
    "team": "Morocco",
    "p": 1,
    "w": 0,
    "d": 1,
    "l": 0,
    "gf": 1,
    "ga": 1,
    "pts": 1,
    "gd": 0
   },
   {
    "team": "Haiti",
    "p": 1,
    "w": 0,
    "d": 0,
    "l": 1,
    "gf": 0,
    "ga": 1,
    "pts": 0,
    "gd": -1
   }
  ],
  "Group D": [
   {
    "team": "USA",
    "p": 1,
    "w": 1,
    "d": 0,
    "l": 0,
    "gf": 4,
    "ga": 1,
    "pts": 3,
    "gd": 3
   },
   {
    "team": "Australia",
    "p": 1,
    "w": 1,
    "d": 0,
    "l": 0,
    "gf": 2,
    "ga": 0,
    "pts": 3,
    "gd": 2
   },
   {
    "team": "Turkey",
    "p": 1,
    "w": 0,
    "d": 0,
    "l": 1,
    "gf": 0,
    "ga": 2,
    "pts": 0,
    "gd": -2
   },
   {
    "team": "Paraguay",
    "p": 1,
    "w": 0,
    "d": 0,
    "l": 1,
    "gf": 1,
    "ga": 4,
    "pts": 0,
    "gd": -3
   }
  ],
  "Group E": [
   {
    "team": "Germany",
    "p": 1,
    "w": 1,
    "d": 0,
    "l": 0,
    "gf": 7,
    "ga": 1,
    "pts": 3,
    "gd": 6
   },
   {
    "team": "Ivory Coast",
    "p": 1,
    "w": 1,
    "d": 0,
    "l": 0,
    "gf": 1,
    "ga": 0,
    "pts": 3,
    "gd": 1
   },
   {
    "team": "Ecuador",
    "p": 1,
    "w": 0,
    "d": 0,
    "l": 1,
    "gf": 0,
    "ga": 1,
    "pts": 0,
    "gd": -1
   },
   {
    "team": "Curaçao",
    "p": 1,
    "w": 0,
    "d": 0,
    "l": 1,
    "gf": 1,
    "ga": 7,
    "pts": 0,
    "gd": -6
   }
  ],
  "Group F": [
   {
    "team": "Sweden",
    "p": 1,
    "w": 1,
    "d": 0,
    "l": 0,
    "gf": 5,
    "ga": 1,
    "pts": 3,
    "gd": 4
   },
   {
    "team": "Japan",
    "p": 1,
    "w": 0,
    "d": 1,
    "l": 0,
    "gf": 2,
    "ga": 2,
    "pts": 1,
    "gd": 0
   },
   {
    "team": "Netherlands",
    "p": 1,
    "w": 0,
    "d": 1,
    "l": 0,
    "gf": 2,
    "ga": 2,
    "pts": 1,
    "gd": 0
   },
   {
    "team": "Tunisia",
    "p": 1,
    "w": 0,
    "d": 0,
    "l": 1,
    "gf": 1,
    "ga": 5,
    "pts": 0,
    "gd": -4
   }
  ],
  "Group G": [
   {
    "team": "Iran",
    "p": 1,
    "w": 0,
    "d": 1,
    "l": 0,
    "gf": 2,
    "ga": 2,
    "pts": 1,
    "gd": 0
   },
   {
    "team": "New Zealand",
    "p": 1,
    "w": 0,
    "d": 1,
    "l": 0,
    "gf": 2,
    "ga": 2,
    "pts": 1,
    "gd": 0
   },
   {
    "team": "Belgium",
    "p": 1,
    "w": 0,
    "d": 1,
    "l": 0,
    "gf": 1,
    "ga": 1,
    "pts": 1,
    "gd": 0
   },
   {
    "team": "Egypt",
    "p": 1,
    "w": 0,
    "d": 1,
    "l": 0,
    "gf": 1,
    "ga": 1,
    "pts": 1,
    "gd": 0
   }
  ],
  "Group H": [
   {
    "team": "Saudi Arabia",
    "p": 1,
    "w": 0,
    "d": 1,
    "l": 0,
    "gf": 1,
    "ga": 1,
    "pts": 1,
    "gd": 0
   },
   {
    "team": "Uruguay",
    "p": 1,
    "w": 0,
    "d": 1,
    "l": 0,
    "gf": 1,
    "ga": 1,
    "pts": 1,
    "gd": 0
   },
   {
    "team": "Cape Verde",
    "p": 1,
    "w": 0,
    "d": 1,
    "l": 0,
    "gf": 0,
    "ga": 0,
    "pts": 1,
    "gd": 0
   },
   {
    "team": "Spain",
    "p": 1,
    "w": 0,
    "d": 1,
    "l": 0,
    "gf": 0,
    "ga": 0,
    "pts": 1,
    "gd": 0
   }
  ],
  "Group I": [
   {
    "team": "Norway",
    "p": 1,
    "w": 1,
    "d": 0,
    "l": 0,
    "gf": 4,
    "ga": 1,
    "pts": 3,
    "gd": 3
   },
   {
    "team": "France",
    "p": 1,
    "w": 1,
    "d": 0,
    "l": 0,
    "gf": 3,
    "ga": 1,
    "pts": 3,
    "gd": 2
   },
   {
    "team": "Senegal",
    "p": 1,
    "w": 0,
    "d": 0,
    "l": 1,
    "gf": 1,
    "ga": 3,
    "pts": 0,
    "gd": -2
   },
   {
    "team": "Iraq",
    "p": 1,
    "w": 0,
    "d": 0,
    "l": 1,
    "gf": 1,
    "ga": 4,
    "pts": 0,
    "gd": -3
   }
  ],
  "Group J": [
   {
    "team": "Argentina",
    "p": 1,
    "w": 1,
    "d": 0,
    "l": 0,
    "gf": 3,
    "ga": 0,
    "pts": 3,
    "gd": 3
   },
   {
    "team": "Austria",
    "p": 1,
    "w": 1,
    "d": 0,
    "l": 0,
    "gf": 3,
    "ga": 1,
    "pts": 3,
    "gd": 2
   },
   {
    "team": "Jordan",
    "p": 1,
    "w": 0,
    "d": 0,
    "l": 1,
    "gf": 1,
    "ga": 3,
    "pts": 0,
    "gd": -2
   },
   {
    "team": "Algeria",
    "p": 1,
    "w": 0,
    "d": 0,
    "l": 1,
    "gf": 0,
    "ga": 3,
    "pts": 0,
    "gd": -3
   }
  ],
  "Group K": [
   {
    "team": "DR Congo",
    "p": 1,
    "w": 0,
    "d": 1,
    "l": 0,
    "gf": 1,
    "ga": 1,
    "pts": 1,
    "gd": 0
   },
   {
    "team": "Portugal",
    "p": 1,
    "w": 0,
    "d": 1,
    "l": 0,
    "gf": 1,
    "ga": 1,
    "pts": 1,
    "gd": 0
   },
   {
    "team": "Colombia",
    "p": 0,
    "w": 0,
    "d": 0,
    "l": 0,
    "gf": 0,
    "ga": 0,
    "pts": 0,
    "gd": 0
   },
   {
    "team": "Uzbekistan",
    "p": 0,
    "w": 0,
    "d": 0,
    "l": 0,
    "gf": 0,
    "ga": 0,
    "pts": 0,
    "gd": 0
   }
  ],
  "Group L": [
   {
    "team": "Croatia",
    "p": 0,
    "w": 0,
    "d": 0,
    "l": 0,
    "gf": 0,
    "ga": 0,
    "pts": 0,
    "gd": 0
   },
   {
    "team": "England",
    "p": 0,
    "w": 0,
    "d": 0,
    "l": 0,
    "gf": 0,
    "ga": 0,
    "pts": 0,
    "gd": 0
   },
   {
    "team": "Ghana",
    "p": 0,
    "w": 0,
    "d": 0,
    "l": 0,
    "gf": 0,
    "ga": 0,
    "pts": 0,
    "gd": 0
   },
   {
    "team": "Panama",
    "p": 0,
    "w": 0,
    "d": 0,
    "l": 0,
    "gf": 0,
    "ga": 0,
    "pts": 0,
    "gd": 0
   }
  ]
 }
}